plotpage/__init__.py
plotpage/cache.py
plotpage/highlight-github.css
plotpage/highlight.pack.js
plotpage/output.py
plotpage/plot.py
plotpage/render.py
plotpage-0.1.0.dist-info/METADATA
plotpage-0.1.0.dist-info/WHEEL
plotpage-0.1.0.dist-info/top_level.txt
plotpage-0.1.0.dist-info/RECORD
